{
  "docs": {
    "Getting Started": [
      "introduction",
      "migration",
      "terminology"
    ],
    "PlaceHolderView": [
      "phv-view-definition",
      "phv-view-builder",
      "phv-view-adapter",
      "phv-view-operations",
      "phv-view-sort"
    ],
    "InfinitePlaceHolderView": [
      "iphv-intro"
    ],
    "ExpandablePlaceHolderView": [
      "ephv-intro",
      "ephv-parent",
      "ephv-child",
      "ephv-view-operations"
    ],
    "SwipePlaceHolderView": [
      "sphv-intro",
      "sphv-view-definition",
      "sphv-view-decor",
      "sphv-view-builder",
      "sphv-view-operations"
    ],
    "SwipeDirectionalView": [
      "sdv-intro"
    ]
  }
}